spsspro/__init__.py
spsspro/algorithm/__init__.py
spsspro/algorithm/supervised_learning.py
spsspro-0.1.1.dist-info/METADATA
spsspro-0.1.1.dist-info/WHEEL
spsspro-0.1.1.dist-info/top_level.txt
spsspro-0.1.1.dist-info/RECORD
